perconet/__init__.py
perconet/loopfinder.py
perconet/looptools.py
perconet/periodicnetwork.py
perconet-0.4.3.dist-info/METADATA
perconet-0.4.3.dist-info/WHEEL
perconet-0.4.3.dist-info/licenses/LICENSE
perconet-0.4.3.dist-info/RECORD
