Metadata-Version: 2.4
Name: perconet
Version: 0.4.3
Summary: Analyze percolation properties of periodic networks
License-Expression: EUPL-1.2
License-File: LICENSE
Author: Chiara Raffaelli and Wouter Ellenbroek
Requires-Python: >=3.8,<3.15
Classifier: Development Status :: 4 - Beta
Classifier: Intended Audience :: Science/Research
Classifier: License :: OSI Approved :: European Union Public Licence 1.2 (EUPL 1.2)
Classifier: Programming Language :: Python :: 3
Classifier: Programming Language :: Python :: 3.8
Classifier: Programming Language :: Python :: 3.9
Classifier: Programming Language :: Python :: 3.10
Classifier: Programming Language :: Python :: 3.11
Classifier: Programming Language :: Python :: 3.12
Classifier: Programming Language :: Python :: 3.13
Classifier: Programming Language :: Python :: 3.14
Requires-Dist: numpy (>=1.23,<1.25) ; python_version == "3.8"
Requires-Dist: numpy (>=1.23,<2.4) ; python_version >= "3.9" and python_version < "3.12"
Requires-Dist: numpy (>=1.26,<2.4) ; python_version >= "3.12" and python_version < "3.15"
Project-URL: Documentation, https://perconet.readthedocs.io/
Project-URL: Repository, https://github.com/wouterel/perconet
